{"frames":{"spr0_f0":{"frame":{"x":0,"y":0,"w":89,"h":121},"rotated":false,"trimmed":false,"spriteSourceSize":{"x":0,"y":0,"w":89,"h":121},"sourceSize":{"w":89,"h":121},"pivot":{"x":-0.5056179775280899,"y":-0.7603305785123967}},"spr0_f1":{"frame":{"x":178,"y":0,"w":89,"h":124},"rotated":false,"trimmed":false,"spriteSourceSize":{"x":0,"y":0,"w":89,"h":124},"sourceSize":{"w":89,"h":124},"pivot":{"x":-0.5056179775280899,"y":-0.7419354838709677}},"spr0_f2":{"frame":{"x":356,"y":0,"w":89,"h":125},"rotated":false,"trimmed":false,"spriteSourceSize":{"x":0,"y":0,"w":89,"h":125},"sourceSize":{"w":89,"h":125},"pivot":{"x":-0.5056179775280899,"y":-0.728}},"spr0_f3":{"frame":{"x":534,"y":0,"w":87,"h":128},"rotated":false,"trimmed":false,"spriteSourceSize":{"x":0,"y":0,"w":87,"h":128},"sourceSize":{"w":87,"h":128},"pivot":{"x":-0.5057471264367817,"y":-0.7109375}},"spr0_f4":{"frame":{"x":712,"y":0,"w":88,"h":128},"rotated":false,"trimmed":false,"spriteSourceSize":{"x":0,"y":0,"w":88,"h":128},"sourceSize":{"w":88,"h":128},"pivot":{"x":-0.5113636363636364,"y":-0.7109375}},"spr0_f5":{"frame":{"x":890,"y":0,"w":89,"h":128},"rotated":false,"trimmed":false,"spriteSourceSize":{"x":0,"y":0,"w":89,"h":128},"sourceSize":{"w":89,"h":128},"pivot":{"x":-0.5056179775280899,"y":-0.7265625}},"spr0_f6":{"frame":{"x":1068,"y":0,"w":89,"h":124},"rotated":false,"trimmed":false,"spriteSourceSize":{"x":0,"y":0,"w":89,"h":124},"sourceSize":{"w":89,"h":124},"pivot":{"x":-0.5056179775280899,"y":-0.7419354838709677}},"spr0_f7":{"frame":{"x":1246,"y":0,"w":89,"h":121},"rotated":false,"trimmed":false,"spriteSourceSize":{"x":0,"y":0,"w":89,"h":121},"sourceSize":{"w":89,"h":121},"pivot":{"x":-0.5056179775280899,"y":-0.7603305785123967}},"spr10_f0":{"frame":{"x":1958,"y":456,"w":153,"h":132},"rotated":false,"trimmed":false,"spriteSourceSize":{"x":0,"y":0,"w":153,"h":132},"sourceSize":{"w":153,"h":132},"pivot":{"x":-0.7581699346405228,"y":-0.9166666666666666}},"spr10_f1":{"frame":{"x":2136,"y":456,"w":153,"h":129},"rotated":false,"trimmed":false,"spriteSourceSize":{"x":0,"y":0,"w":153,"h":129},"sourceSize":{"w":153,"h":129},"pivot":{"x":-0.7843137254901961,"y":-0.9457364341085271}},"spr10_f2":{"frame":{"x":2314,"y":456,"w":149,"h":130},"rotated":false,"trimmed":false,"spriteSourceSize":{"x":0,"y":0,"w":149,"h":130},"sourceSize":{"w":149,"h":130},"pivot":{"x":-0.8053691275167785,"y":-0.9615384615384616}},"spr10_f3":{"frame":{"x":2492,"y":456,"w":151,"h":124},"rotated":false,"trimmed":false,"spriteSourceSize":{"x":0,"y":0,"w":151,"h":124},"sourceSize":{"w":151,"h":124},"pivot":{"x":-0.7814569536423841,"y":-0.9838709677419355}},"spr10_f4":{"frame":{"x":2670,"y":456,"w":153,"h":131},"rotated":false,"trimmed":false,"spriteSourceSize":{"x":0,"y":0,"w":153,"h":131},"sourceSize":{"w":153,"h":131},"pivot":{"x":-0.7581699346405228,"y":-0.9236641221374046}},"spr10_f5":{"frame":{"x":2848,"y":456,"w":152,"h":132},"rotated":false,"trimmed":false,"spriteSourceSize":{"x":0,"y":0,"w":152,"h":132},"sourceSize":{"w":152,"h":132},"pivot":{"x":-0.7828947368421053,"y":-0.9242424242424242}},"spr10_f6":{"frame":{"x":3026,"y":456,"w":149,"h":135},"rotated":false,"trimmed":false,"spriteSourceSize":{"x":0,"y":0,"w":149,"h":135},"sourceSize":{"w":149,"h":135},"pivot":{"x":-0.8053691275167785,"y":-0.9259259259259259}},"spr10_f7":{"frame":{"x":3204,"y":456,"w":152,"h":132},"rotated":false,"trimmed":false,"spriteSourceSize":{"x":0,"y":0,"w":152,"h":132},"sourceSize":{"w":152,"h":132},"pivot":{"x":-0.7828947368421053,"y":-0.9242424242424242}},"spr11_f0":{"frame":{"x":3382,"y":456,"w":102,"h":135},"rotated":false,"trimmed":false,"spriteSourceSize":{"x":0,"y":0,"w":102,"h":135},"sourceSize":{"w":102,"h":135},"pivot":{"x":-0.7549019607843137,"y":-0.9777777777777777}},"spr11_f1":{"frame":{"x":3560,"y":456,"w":94,"h":137},"rotated":false,"trimmed":false,"spriteSourceSize":{"x":0,"y":0,"w":94,"h":137},"sourceSize":{"w":94,"h":137},"pivot":{"x":-0.7446808510638298,"y":-0.9854014598540146}},"spr11_f2":{"frame":{"x":3738,"y":456,"w":92,"h":137},"rotated":false,"trimmed":false,"spriteSourceSize":{"x":0,"y":0,"w":92,"h":137},"sourceSize":{"w":92,"h":137},"pivot":{"x":-0.75,"y":-1.0072992700729928}},"spr11_f3":{"frame":{"x":3916,"y":456,"w":95,"h":131},"rotated":false,"trimmed":false,"spriteSourceSize":{"x":0,"y":0,"w":95,"h":131},"sourceSize":{"w":95,"h":131},"pivot":{"x":-0.7368421052631579,"y":-1.0305343511450382}},"spr11_f4":{"frame":{"x":0,"y":608,"w":99,"h":142},"rotated":false,"trimmed":false,"spriteSourceSize":{"x":0,"y":0,"w":99,"h":142},"sourceSize":{"w":99,"h":142},"pivot":{"x":-0.7373737373737373,"y":-0.9295774647887324}},"spr11_f5":{"frame":{"x":178,"y":608,"w":94,"h":142},"rotated":false,"trimmed":false,"spriteSourceSize":{"x":0,"y":0,"w":94,"h":142},"sourceSize":{"w":94,"h":142},"pivot":{"x":-0.7446808510638298,"y":-0.9507042253521126}},"spr11_f6":{"frame":{"x":356,"y":608,"w":88,"h":142},"rotated":false,"trimmed":false,"spriteSourceSize":{"x":0,"y":0,"w":88,"h":142},"sourceSize":{"w":88,"h":142},"pivot":{"x":-0.7840909090909091,"y":-0.971830985915493}},"spr11_f7":{"frame":{"x":534,"y":608,"w":92,"h":136},"rotated":false,"trimmed":false,"spriteSourceSize":{"x":0,"y":0,"w":92,"h":136},"sourceSize":{"w":92,"h":136},"pivot":{"x":-0.7608695652173914,"y":-0.9926470588235294}},"spr12_f0":{"frame":{"x":712,"y":608,"w":89,"h":136},"rotated":false,"trimmed":false,"spriteSourceSize":{"x":0,"y":0,"w":89,"h":136},"sourceSize":{"w":89,"h":136},"pivot":{"x":-0.5056179775280899,"y":-0.9485294117647058}},"spr12_f1":{"frame":{"x":890,"y":608,"w":87,"h":140},"rotated":false,"trimmed":false,"spriteSourceSize":{"x":0,"y":0,"w":87,"h":140},"sourceSize":{"w":87,"h":140},"pivot":{"x":-0.5057471264367817,"y":-0.9571428571428572}},"spr12_f2":{"frame":{"x":1068,"y":608,"w":85,"h":140},"rotated":false,"trimmed":false,"spriteSourceSize":{"x":0,"y":0,"w":85,"h":140},"sourceSize":{"w":85,"h":140},"pivot":{"x":-0.5058823529411764,"y":-0.9785714285714285}},"spr12_f3":{"frame":{"x":1246,"y":608,"w":87,"h":133},"rotated":false,"trimmed":false,"spriteSourceSize":{"x":0,"y":0,"w":87,"h":133},"sourceSize":{"w":87,"h":133},"pivot":{"x":-0.5057471264367817,"y":-1.0075187969924813}},"spr12_f4":{"frame":{"x":1424,"y":608,"w":89,"h":136},"rotated":false,"trimmed":false,"spriteSourceSize":{"x":0,"y":0,"w":89,"h":136},"sourceSize":{"w":89,"h":136},"pivot":{"x":-0.5056179775280899,"y":-0.9485294117647058}},"spr12_f5":{"frame":{"x":1602,"y":608,"w":87,"h":138},"rotated":false,"trimmed":false,"spriteSourceSize":{"x":0,"y":0,"w":87,"h":138},"sourceSize":{"w":87,"h":138},"pivot":{"x":-0.5057471264367817,"y":-0.9710144927536232}},"spr12_f6":{"frame":{"x":1780,"y":608,"w":85,"h":137},"rotated":false,"trimmed":false,"spriteSourceSize":{"x":0,"y":0,"w":85,"h":137},"sourceSize":{"w":85,"h":137},"pivot":{"x":-0.5058823529411764,"y":-1}},"spr12_f7":{"frame":{"x":1958,"y":608,"w":87,"h":131},"rotated":false,"trimmed":false,"spriteSourceSize":{"x":0,"y":0,"w":87,"h":131},"sourceSize":{"w":87,"h":131},"pivot":{"x":-0.5057471264367817,"y":-1.0229007633587786}},"spr13_f0":{"frame":{"x":2136,"y":608,"w":100,"h":142},"rotated":false,"trimmed":false,"spriteSourceSize":{"x":0,"y":0,"w":100,"h":142},"sourceSize":{"w":100,"h":142},"pivot":{"x":-0.28,"y":-0.9295774647887324}},"spr13_f1":{"frame":{"x":2314,"y":608,"w":95,"h":144},"rotated":false,"trimmed":false,"spriteSourceSize":{"x":0,"y":0,"w":95,"h":144},"sourceSize":{"w":95,"h":144},"pivot":{"x":-0.2631578947368421,"y":-0.9375}},"spr13_f2":{"frame":{"x":2492,"y":608,"w":89,"h":144},"rotated":false,"trimmed":false,"spriteSourceSize":{"x":0,"y":0,"w":89,"h":144},"sourceSize":{"w":89,"h":144},"pivot":{"x":-0.2247191011235955,"y":-0.9583333333333334}},"spr13_f3":{"frame":{"x":2670,"y":608,"w":96,"h":138},"rotated":false,"trimmed":false,"spriteSourceSize":{"x":0,"y":0,"w":96,"h":138},"sourceSize":{"w":96,"h":138},"pivot":{"x":-0.23958333333333334,"y":-0.9782608695652174}},"spr13_f4":{"frame":{"x":2848,"y":608,"w":103,"h":135},"rotated":false,"trimmed":false,"spriteSourceSize":{"x":0,"y":0,"w":103,"h":135},"sourceSize":{"w":103,"h":135},"pivot":{"x":-0.2524271844660194,"y":-0.9777777777777777}},"spr13_f5":{"frame":{"x":3026,"y":608,"w":95,"h":135},"rotated":false,"trimmed":false,"spriteSourceSize":{"x":0,"y":0,"w":95,"h":135},"sourceSize":{"w":95,"h":135},"pivot":{"x":-0.23157894736842105,"y":-1}},"spr13_f6":{"frame":{"x":3204,"y":608,"w":93,"h":137},"rotated":false,"trimmed":false,"spriteSourceSize":{"x":0,"y":0,"w":93,"h":137},"sourceSize":{"w":93,"h":137},"pivot":{"x":-0.25806451612903225,"y":-1.0072992700729928}},"spr13_f7":{"frame":{"x":3382,"y":608,"w":97,"h":130},"rotated":false,"trimmed":false,"spriteSourceSize":{"x":0,"y":0,"w":97,"h":130},"sourceSize":{"w":97,"h":130},"pivot":{"x":-0.27835051546391754,"y":-1.0384615384615385}},"spr14_f0":{"frame":{"x":3560,"y":608,"w":153,"h":132},"rotated":false,"trimmed":false,"spriteSourceSize":{"x":0,"y":0,"w":153,"h":132},"sourceSize":{"w":153,"h":132},"pivot":{"x":-0.24836601307189543,"y":-0.9242424242424242}},"spr14_f1":{"frame":{"x":3738,"y":608,"w":152,"h":133},"rotated":false,"trimmed":false,"spriteSourceSize":{"x":0,"y":0,"w":152,"h":133},"sourceSize":{"w":152,"h":133},"pivot":{"x":-0.2236842105263158,"y":-0.924812030075188}},"spr14_f2":{"frame":{"x":3916,"y":608,"w":149,"h":135},"rotated":false,"trimmed":false,"spriteSourceSize":{"x":0,"y":0,"w":149,"h":135},"sourceSize":{"w":149,"h":135},"pivot":{"x":-0.20134228187919462,"y":-0.9259259259259259}},"spr14_f3":{"frame":{"x":0,"y":760,"w":151,"h":133},"rotated":false,"trimmed":false,"spriteSourceSize":{"x":0,"y":0,"w":151,"h":133},"sourceSize":{"w":151,"h":133},"pivot":{"x":-0.2251655629139073,"y":-0.924812030075188}},"spr14_f4":{"frame":{"x":178,"y":760,"w":153,"h":132},"rotated":false,"trimmed":false,"spriteSourceSize":{"x":0,"y":0,"w":153,"h":132},"sourceSize":{"w":153,"h":132},"pivot":{"x":-0.24836601307189543,"y":-0.9242424242424242}},"spr14_f5":{"frame":{"x":356,"y":760,"w":152,"h":128},"rotated":false,"trimmed":false,"spriteSourceSize":{"x":0,"y":0,"w":152,"h":128},"sourceSize":{"w":152,"h":128},"pivot":{"x":-0.2236842105263158,"y":-0.953125}},"spr14_f6":{"frame":{"x":534,"y":760,"w":149,"h":130},"rotated":false,"trimmed":false,"spriteSourceSize":{"x":0,"y":0,"w":149,"h":130},"sourceSize":{"w":149,"h":130},"pivot":{"x":-0.20134228187919462,"y":-0.9615384615384616}},"spr14_f7":{"frame":{"x":712,"y":760,"w":152,"h":124},"rotated":false,"trimmed":false,"spriteSourceSize":{"x":0,"y":0,"w":152,"h":124},"sourceSize":{"w":152,"h":124},"pivot":{"x":-0.2236842105263158,"y":-0.9838709677419355}},"spr15_f0":{"frame":{"x":890,"y":760,"w":102,"h":119},"rotated":false,"trimmed":false,"spriteSourceSize":{"x":0,"y":0,"w":102,"h":119},"sourceSize":{"w":102,"h":119},"pivot":{"x":-0.2549019607843137,"y":-0.8403361344537815}},"spr15_f1":{"frame":{"x":1068,"y":760,"w":95,"h":125},"rotated":false,"trimmed":false,"spriteSourceSize":{"x":0,"y":0,"w":95,"h":125},"sourceSize":{"w":95,"h":125},"pivot":{"x":-0.2631578947368421,"y":-0.816}},"spr15_f2":{"frame":{"x":1246,"y":760,"w":93,"h":135},"rotated":false,"trimmed":false,"spriteSourceSize":{"x":0,"y":0,"w":93,"h":135},"sourceSize":{"w":93,"h":135},"pivot":{"x":-0.25806451612903225,"y":-0.7777777777777778}},"spr15_f3":{"frame":{"x":1424,"y":760,"w":95,"h":131},"rotated":false,"trimmed":false,"spriteSourceSize":{"x":0,"y":0,"w":95,"h":131},"sourceSize":{"w":95,"h":131},"pivot":{"x":-0.2736842105263158,"y":-0.7786259541984732}},"spr15_f4":{"frame":{"x":1602,"y":760,"w":99,"h":126},"rotated":false,"trimmed":false,"spriteSourceSize":{"x":0,"y":0,"w":99,"h":126},"sourceSize":{"w":99,"h":126},"pivot":{"x":-0.2727272727272727,"y":-0.7936507936507936}},"spr15_f5":{"frame":{"x":1780,"y":760,"w":94,"h":130},"rotated":false,"trimmed":false,"spriteSourceSize":{"x":0,"y":0,"w":94,"h":130},"sourceSize":{"w":94,"h":130},"pivot":{"x":-0.26595744680851063,"y":-0.7846153846153846}},"spr15_f6":{"frame":{"x":1958,"y":760,"w":89,"h":133},"rotated":false,"trimmed":false,"spriteSourceSize":{"x":0,"y":0,"w":89,"h":133},"sourceSize":{"w":89,"h":133},"pivot":{"x":-0.2247191011235955,"y":-0.7894736842105263}},"spr15_f7":{"frame":{"x":2136,"y":760,"w":92,"h":124},"rotated":false,"trimmed":false,"spriteSourceSize":{"x":0,"y":0,"w":92,"h":124},"sourceSize":{"w":92,"h":124},"pivot":{"x":-0.2391304347826087,"y":-0.8225806451612904}},"spr16_f0":{"frame":{"x":2314,"y":760,"w":89,"h":121},"rotated":false,"trimmed":false,"spriteSourceSize":{"x":0,"y":0,"w":89,"h":121},"sourceSize":{"w":89,"h":121},"pivot":{"x":-0.5056179775280899,"y":-0.7603305785123967}},"spr16_f1":{"frame":{"x":2492,"y":760,"w":91,"h":110},"rotated":false,"trimmed":false,"spriteSourceSize":{"x":0,"y":0,"w":91,"h":110},"sourceSize":{"w":91,"h":110},"pivot":{"x":-0.5054945054945055,"y":-0.8454545454545455}},"spr16_f2":{"frame":{"x":2670,"y":760,"w":98,"h":109},"rotated":false,"trimmed":false,"spriteSourceSize":{"x":0,"y":0,"w":98,"h":109},"sourceSize":{"w":98,"h":109},"pivot":{"x":-0.5102040816326531,"y":-0.8715596330275229}},"spr16_f3":{"frame":{"x":2848,"y":760,"w":91,"h":119},"rotated":false,"trimmed":false,"spriteSourceSize":{"x":0,"y":0,"w":91,"h":119},"sourceSize":{"w":91,"h":119},"pivot":{"x":-0.5054945054945055,"y":-0.8067226890756303}},"spr16_f4":{"frame":{"x":3026,"y":760,"w":83,"h":141},"rotated":false,"trimmed":false,"spriteSourceSize":{"x":0,"y":0,"w":83,"h":141},"sourceSize":{"w":83,"h":141},"pivot":{"x":-0.5060240963855421,"y":-0.723404255319149}},"spr16_f5":{"frame":{"x":3204,"y":760,"w":85,"h":148},"rotated":false,"trimmed":false,"spriteSourceSize":{"x":0,"y":0,"w":85,"h":148},"sourceSize":{"w":85,"h":148},"pivot":{"x":-0.5058823529411764,"y":-0.7297297297297297}},"spr16_f6":{"frame":{"x":3382,"y":760,"w":89,"h":137},"rotated":false,"trimmed":false,"spriteSourceSize":{"x":0,"y":0,"w":89,"h":137},"sourceSize":{"w":89,"h":137},"pivot":{"x":-0.5056179775280899,"y":-0.7445255474452555}},"spr16_f7":{"frame":{"x":3560,"y":760,"w":89,"h":121},"rotated":false,"trimmed":false,"spriteSourceSize":{"x":0,"y":0,"w":89,"h":121},"sourceSize":{"w":89,"h":121},"pivot":{"x":-0.5056179775280899,"y":-0.7603305785123967}},"spr17_f0":{"frame":{"x":3738,"y":760,"w":99,"h":127},"rotated":false,"trimmed":false,"spriteSourceSize":{"x":0,"y":0,"w":99,"h":127},"sourceSize":{"w":99,"h":127},"pivot":{"x":-0.7272727272727273,"y":-0.7874015748031497}},"spr17_f1":{"frame":{"x":3916,"y":760,"w":105,"h":116},"rotated":false,"trimmed":false,"spriteSourceSize":{"x":0,"y":0,"w":105,"h":116},"sourceSize":{"w":105,"h":116},"pivot":{"x":-0.7619047619047619,"y":-0.853448275862069}},"spr17_f2":{"frame":{"x":0,"y":912,"w":111,"h":116},"rotated":false,"trimmed":false,"spriteSourceSize":{"x":0,"y":0,"w":111,"h":116},"sourceSize":{"w":111,"h":116},"pivot":{"x":-0.7837837837837838,"y":-0.8620689655172413}},"spr17_f3":{"frame":{"x":178,"y":912,"w":101,"h":124},"rotated":false,"trimmed":false,"spriteSourceSize":{"x":0,"y":0,"w":101,"h":124},"sourceSize":{"w":101,"h":124},"pivot":{"x":-0.693069306930693,"y":-0.8306451612903226}},"spr17_f4":{"frame":{"x":356,"y":912,"w":84,"h":140},"rotated":false,"trimmed":false,"spriteSourceSize":{"x":0,"y":0,"w":84,"h":140},"sourceSize":{"w":84,"h":140},"pivot":{"x":-0.6785714285714286,"y":-0.7214285714285714}},"spr17_f5":{"frame":{"x":534,"y":912,"w":89,"h":144},"rotated":false,"trimmed":false,"spriteSourceSize":{"x":0,"y":0,"w":89,"h":144},"sourceSize":{"w":89,"h":144},"pivot":{"x":-0.6741573033707865,"y":-0.7291666666666666}},"spr17_f6":{"frame":{"x":712,"y":912,"w":97,"h":134},"rotated":false,"trimmed":false,"spriteSourceSize":{"x":0,"y":0,"w":97,"h":134},"sourceSize":{"w":97,"h":134},"pivot":{"x":-0.7010309278350515,"y":-0.746268656716418}},"spr17_f7":{"frame":{"x":890,"y":912,"w":99,"h":127},"rotated":false,"trimmed":false,"spriteSourceSize":{"x":0,"y":0,"w":99,"h":127},"sourceSize":{"w":99,"h":127},"pivot":{"x":-0.7272727272727273,"y":-0.7874015748031497}},"spr18_f0":{"frame":{"x":1068,"y":912,"w":153,"h":132},"rotated":false,"trimmed":false,"spriteSourceSize":{"x":0,"y":0,"w":153,"h":132},"sourceSize":{"w":153,"h":132},"pivot":{"x":-0.7581699346405228,"y":-0.9166666666666666}},"spr18_f1":{"frame":{"x":1246,"y":912,"w":147,"h":133},"rotated":false,"trimmed":false,"spriteSourceSize":{"x":0,"y":0,"w":147,"h":133},"sourceSize":{"w":147,"h":133},"pivot":{"x":-0.8027210884353742,"y":-0.9172932330827067}},"spr18_f2":{"frame":{"x":1424,"y":912,"w":139,"h":134},"rotated":false,"trimmed":false,"spriteSourceSize":{"x":0,"y":0,"w":139,"h":134},"sourceSize":{"w":139,"h":134},"pivot":{"x":-0.841726618705036,"y":-0.917910447761194}},"spr18_f3":{"frame":{"x":1602,"y":912,"w":154,"h":133},"rotated":false,"trimmed":false,"spriteSourceSize":{"x":0,"y":0,"w":154,"h":133},"sourceSize":{"w":154,"h":133},"pivot":{"x":-0.7142857142857143,"y":-0.9172932330827067}},"spr18_f4":{"frame":{"x":1780,"y":912,"w":159,"h":126},"rotated":false,"trimmed":false,"spriteSourceSize":{"x":0,"y":0,"w":159,"h":126},"sourceSize":{"w":159,"h":126},"pivot":{"x":-0.6037735849056604,"y":-0.9126984126984127}},"spr18_f5":{"frame":{"x":1958,"y":912,"w":148,"h":127},"rotated":false,"trimmed":false,"spriteSourceSize":{"x":0,"y":0,"w":148,"h":127},"sourceSize":{"w":148,"h":127},"pivot":{"x":-0.6824324324324325,"y":-0.9133858267716536}},"spr18_f6":{"frame":{"x":2136,"y":912,"w":149,"h":131},"rotated":false,"trimmed":false,"spriteSourceSize":{"x":0,"y":0,"w":149,"h":131},"sourceSize":{"w":149,"h":131},"pivot":{"x":-0.7449664429530202,"y":-0.916030534351145}},"spr18_f7":{"frame":{"x":2314,"y":912,"w":153,"h":132},"rotated":false,"trimmed":false,"spriteSourceSize":{"x":0,"y":0,"w":153,"h":132},"sourceSize":{"w":153,"h":132},"pivot":{"x":-0.7581699346405228,"y":-0.9166666666666666}},"spr19_f0":{"frame":{"x":2492,"y":912,"w":102,"h":135},"rotated":false,"trimmed":false,"spriteSourceSize":{"x":0,"y":0,"w":102,"h":135},"sourceSize":{"w":102,"h":135},"pivot":{"x":-0.7549019607843137,"y":-0.9777777777777777}},"spr19_f1":{"frame":{"x":2670,"y":912,"w":105,"h":140},"rotated":false,"trimmed":false,"spriteSourceSize":{"x":0,"y":0,"w":105,"h":140},"sourceSize":{"w":105,"h":140},"pivot":{"x":-0.7619047619047619,"y":-0.9785714285714285}},"spr19_f2":{"frame":{"x":2848,"y":912,"w":112,"h":143},"rotated":false,"trimmed":false,"spriteSourceSize":{"x":0,"y":0,"w":112,"h":143},"sourceSize":{"w":112,"h":143},"pivot":{"x":-0.7767857142857143,"y":-0.9790209790209791}},"spr19_f3":{"frame":{"x":3026,"y":912,"w":98,"h":133},"rotated":false,"trimmed":false,"spriteSourceSize":{"x":0,"y":0,"w":98,"h":133},"sourceSize":{"w":98,"h":133},"pivot":{"x":-0.7448979591836735,"y":-0.9774436090225563}},"spr19_f4":{"frame":{"x":3204,"y":912,"w":104,"h":119},"rotated":false,"trimmed":false,"spriteSourceSize":{"x":0,"y":0,"w":104,"h":119},"sourceSize":{"w":104,"h":119},"pivot":{"x":-0.6442307692307693,"y":-0.9747899159663865}},"spr19_f5":{"frame":{"x":3382,"y":912,"w":99,"h":122},"rotated":false,"trimmed":false,"spriteSourceSize":{"x":0,"y":0,"w":99,"h":122},"sourceSize":{"w":99,"h":122},"pivot":{"x":-0.696969696969697,"y":-0.9754098360655737}},"spr19_f6":{"frame":{"x":3560,"y":912,"w":99,"h":131},"rotated":false,"trimmed":false,"spriteSourceSize":{"x":0,"y":0,"w":99,"h":131},"sourceSize":{"w":99,"h":131},"pivot":{"x":-0.7474747474747475,"y":-0.9770992366412213}},"spr19_f7":{"frame":{"x":3738,"y":912,"w":102,"h":135},"rotated":false,"trimmed":false,"spriteSourceSize":{"x":0,"y":0,"w":102,"h":135},"sourceSize":{"w":102,"h":135},"pivot":{"x":-0.7549019607843137,"y":-0.9777777777777777}},"spr1_f0":{"frame":{"x":1424,"y":0,"w":99,"h":127},"rotated":false,"trimmed":false,"spriteSourceSize":{"x":0,"y":0,"w":99,"h":127},"sourceSize":{"w":99,"h":127},"pivot":{"x":-0.7272727272727273,"y":-0.7874015748031497}},"spr1_f1":{"frame":{"x":1602,"y":0,"w":99,"h":128},"rotated":false,"trimmed":false,"spriteSourceSize":{"x":0,"y":0,"w":99,"h":128},"sourceSize":{"w":99,"h":128},"pivot":{"x":-0.7272727272727273,"y":-0.7734375}},"spr1_f2":{"frame":{"x":1780,"y":0,"w":98,"h":130},"rotated":false,"trimmed":false,"spriteSourceSize":{"x":0,"y":0,"w":98,"h":130},"sourceSize":{"w":98,"h":130},"pivot":{"x":-0.7244897959183674,"y":-0.7538461538461538}},"spr1_f3":{"frame":{"x":1958,"y":0,"w":98,"h":131},"rotated":false,"trimmed":false,"spriteSourceSize":{"x":0,"y":0,"w":98,"h":131},"sourceSize":{"w":98,"h":131},"pivot":{"x":-0.7244897959183674,"y":-0.7404580152671756}},"spr1_f4":{"frame":{"x":2136,"y":0,"w":98,"h":132},"rotated":false,"trimmed":false,"spriteSourceSize":{"x":0,"y":0,"w":98,"h":132},"sourceSize":{"w":98,"h":132},"pivot":{"x":-0.7244897959183674,"y":-0.7348484848484849}},"spr1_f5":{"frame":{"x":2314,"y":0,"w":99,"h":131},"rotated":false,"trimmed":false,"spriteSourceSize":{"x":0,"y":0,"w":99,"h":131},"sourceSize":{"w":99,"h":131},"pivot":{"x":-0.7272727272727273,"y":-0.7480916030534351}},"spr1_f6":{"frame":{"x":2492,"y":0,"w":99,"h":129},"rotated":false,"trimmed":false,"spriteSourceSize":{"x":0,"y":0,"w":99,"h":129},"sourceSize":{"w":99,"h":129},"pivot":{"x":-0.7272727272727273,"y":-0.7674418604651163}},"spr1_f7":{"frame":{"x":2670,"y":0,"w":99,"h":127},"rotated":false,"trimmed":false,"spriteSourceSize":{"x":0,"y":0,"w":99,"h":127},"sourceSize":{"w":99,"h":127},"pivot":{"x":-0.7272727272727273,"y":-0.7874015748031497}},"spr20_f0":{"frame":{"x":3916,"y":912,"w":89,"h":136},"rotated":false,"trimmed":false,"spriteSourceSize":{"x":0,"y":0,"w":89,"h":136},"sourceSize":{"w":89,"h":136},"pivot":{"x":-0.5056179775280899,"y":-0.9485294117647058}},"spr20_f1":{"frame":{"x":0,"y":1064,"w":91,"h":142},"rotated":false,"trimmed":false,"spriteSourceSize":{"x":0,"y":0,"w":91,"h":142},"sourceSize":{"w":91,"h":142},"pivot":{"x":-0.5054945054945055,"y":-0.9507042253521126}},"spr20_f2":{"frame":{"x":178,"y":1064,"w":98,"h":145},"rotated":false,"trimmed":false,"spriteSourceSize":{"x":0,"y":0,"w":98,"h":145},"sourceSize":{"w":98,"h":145},"pivot":{"x":-0.5,"y":-0.9517241379310345}},"spr20_f3":{"frame":{"x":356,"y":1064,"w":91,"h":133},"rotated":false,"trimmed":false,"spriteSourceSize":{"x":0,"y":0,"w":91,"h":133},"sourceSize":{"w":91,"h":133},"pivot":{"x":-0.5054945054945055,"y":-0.9473684210526315}},"spr20_f4":{"frame":{"x":534,"y":1064,"w":83,"h":118},"rotated":false,"trimmed":false,"spriteSourceSize":{"x":0,"y":0,"w":83,"h":118},"sourceSize":{"w":83,"h":118},"pivot":{"x":-0.5060240963855421,"y":-0.940677966101695}},"spr20_f5":{"frame":{"x":712,"y":1064,"w":85,"h":121},"rotated":false,"trimmed":false,"spriteSourceSize":{"x":0,"y":0,"w":85,"h":121},"sourceSize":{"w":85,"h":121},"pivot":{"x":-0.5058823529411764,"y":-0.9421487603305785}},"spr20_f6":{"frame":{"x":890,"y":1064,"w":89,"h":130},"rotated":false,"trimmed":false,"spriteSourceSize":{"x":0,"y":0,"w":89,"h":130},"sourceSize":{"w":89,"h":130},"pivot":{"x":-0.5056179775280899,"y":-0.9461538461538461}},"spr20_f7":{"frame":{"x":1068,"y":1064,"w":89,"h":136},"rotated":false,"trimmed":false,"spriteSourceSize":{"x":0,"y":0,"w":89,"h":136},"sourceSize":{"w":89,"h":136},"pivot":{"x":-0.5056179775280899,"y":-0.9485294117647058}},"spr21_f0":{"frame":{"x":1246,"y":1064,"w":100,"h":142},"rotated":false,"trimmed":false,"spriteSourceSize":{"x":0,"y":0,"w":100,"h":142},"sourceSize":{"w":100,"h":142},"pivot":{"x":-0.28,"y":-0.9295774647887324}},"spr21_f1":{"frame":{"x":1424,"y":1064,"w":106,"h":147},"rotated":false,"trimmed":false,"spriteSourceSize":{"x":0,"y":0,"w":106,"h":147},"sourceSize":{"w":106,"h":147},"pivot":{"x":-0.24528301886792453,"y":-0.9319727891156463}},"spr21_f2":{"frame":{"x":1602,"y":1064,"w":112,"h":150},"rotated":false,"trimmed":false,"spriteSourceSize":{"x":0,"y":0,"w":112,"h":150},"sourceSize":{"w":112,"h":150},"pivot":{"x":-0.22321428571428573,"y":-0.9333333333333333}},"spr21_f3":{"frame":{"x":1780,"y":1064,"w":101,"h":140},"rotated":false,"trimmed":false,"spriteSourceSize":{"x":0,"y":0,"w":101,"h":140},"sourceSize":{"w":101,"h":140},"pivot":{"x":-0.3069306930693069,"y":-0.9285714285714286}},"spr21_f4":{"frame":{"x":1958,"y":1064,"w":85,"h":126},"rotated":false,"trimmed":false,"spriteSourceSize":{"x":0,"y":0,"w":85,"h":126},"sourceSize":{"w":85,"h":126},"pivot":{"x":-0.3411764705882353,"y":-0.9206349206349206}},"spr21_f5":{"frame":{"x":2136,"y":1064,"w":89,"h":129},"rotated":false,"trimmed":false,"spriteSourceSize":{"x":0,"y":0,"w":89,"h":129},"sourceSize":{"w":89,"h":129},"pivot":{"x":-0.33707865168539325,"y":-0.9224806201550387}},"spr21_f6":{"frame":{"x":2314,"y":1064,"w":97,"h":138},"rotated":false,"trimmed":false,"spriteSourceSize":{"x":0,"y":0,"w":97,"h":138},"sourceSize":{"w":97,"h":138},"pivot":{"x":-0.30927835051546393,"y":-0.927536231884058}},"spr21_f7":{"frame":{"x":2492,"y":1064,"w":100,"h":142},"rotated":false,"trimmed":false,"spriteSourceSize":{"x":0,"y":0,"w":100,"h":142},"sourceSize":{"w":100,"h":142},"pivot":{"x":-0.28,"y":-0.9295774647887324}},"spr22_f0":{"frame":{"x":2670,"y":1064,"w":153,"h":132},"rotated":false,"trimmed":false,"spriteSourceSize":{"x":0,"y":0,"w":153,"h":132},"sourceSize":{"w":153,"h":132},"pivot":{"x":-0.24836601307189543,"y":-0.9242424242424242}},"spr22_f1":{"frame":{"x":2848,"y":1064,"w":147,"h":132},"rotated":false,"trimmed":false,"spriteSourceSize":{"x":0,"y":0,"w":147,"h":132},"sourceSize":{"w":147,"h":132},"pivot":{"x":-0.20408163265306123,"y":-0.9242424242424242}},"spr22_f2":{"frame":{"x":3026,"y":1064,"w":140,"h":134},"rotated":false,"trimmed":false,"spriteSourceSize":{"x":0,"y":0,"w":140,"h":134},"sourceSize":{"w":140,"h":134},"pivot":{"x":-0.17142857142857143,"y":-0.9253731343283582}},"spr22_f3":{"frame":{"x":3204,"y":1064,"w":156,"h":132},"rotated":false,"trimmed":false,"spriteSourceSize":{"x":0,"y":0,"w":156,"h":132},"sourceSize":{"w":156,"h":132},"pivot":{"x":-0.30128205128205127,"y":-0.9242424242424242}},"spr22_f4":{"frame":{"x":3382,"y":1064,"w":159,"h":125},"rotated":false,"trimmed":false,"spriteSourceSize":{"x":0,"y":0,"w":159,"h":125},"sourceSize":{"w":159,"h":125},"pivot":{"x":-0.4025157232704403,"y":-0.92}},"spr22_f5":{"frame":{"x":3560,"y":1064,"w":148,"h":126},"rotated":false,"trimmed":false,"spriteSourceSize":{"x":0,"y":0,"w":148,"h":126},"sourceSize":{"w":148,"h":126},"pivot":{"x":-0.32432432432432434,"y":-0.9206349206349206}},"spr22_f6":{"frame":{"x":3738,"y":1064,"w":149,"h":130},"rotated":false,"trimmed":false,"spriteSourceSize":{"x":0,"y":0,"w":149,"h":130},"sourceSize":{"w":149,"h":130},"pivot":{"x":-0.26174496644295303,"y":-0.9230769230769231}},"spr22_f7":{"frame":{"x":3916,"y":1064,"w":153,"h":132},"rotated":false,"trimmed":false,"spriteSourceSize":{"x":0,"y":0,"w":153,"h":132},"sourceSize":{"w":153,"h":132},"pivot":{"x":-0.24836601307189543,"y":-0.9242424242424242}},"spr23_f0":{"frame":{"x":0,"y":1216,"w":102,"h":119},"rotated":false,"trimmed":false,"spriteSourceSize":{"x":0,"y":0,"w":102,"h":119},"sourceSize":{"w":102,"h":119},"pivot":{"x":-0.2549019607843137,"y":-0.8403361344537815}},"spr23_f1":{"frame":{"x":178,"y":1216,"w":105,"h":116},"rotated":false,"trimmed":false,"spriteSourceSize":{"x":0,"y":0,"w":105,"h":116},"sourceSize":{"w":105,"h":116},"pivot":{"x":-0.24761904761904763,"y":-0.8620689655172413}},"spr23_f2":{"frame":{"x":356,"y":1216,"w":112,"h":115},"rotated":false,"trimmed":false,"spriteSourceSize":{"x":0,"y":0,"w":112,"h":115},"sourceSize":{"w":112,"h":115},"pivot":{"x":-0.23214285714285715,"y":-0.8782608695652174}},"spr23_f3":{"frame":{"x":534,"y":1216,"w":99,"h":119},"rotated":false,"trimmed":false,"spriteSourceSize":{"x":0,"y":0,"w":99,"h":119},"sourceSize":{"w":99,"h":119},"pivot":{"x":-0.26262626262626265,"y":-0.8739495798319328}},"spr23_f4":{"frame":{"x":712,"y":1216,"w":105,"h":130},"rotated":false,"trimmed":false,"spriteSourceSize":{"x":0,"y":0,"w":105,"h":130},"sourceSize":{"w":105,"h":130},"pivot":{"x":-0.37142857142857144,"y":-0.7846153846153846}},"spr23_f5":{"frame":{"x":890,"y":1216,"w":100,"h":132},"rotated":false,"trimmed":false,"spriteSourceSize":{"x":0,"y":0,"w":100,"h":132},"sourceSize":{"w":100,"h":132},"pivot":{"x":-0.31,"y":-0.7878787878787878}},"spr23_f6":{"frame":{"x":1068,"y":1216,"w":100,"h":124},"rotated":false,"trimmed":false,"spriteSourceSize":{"x":0,"y":0,"w":100,"h":124},"sourceSize":{"w":100,"h":124},"pivot":{"x":-0.26,"y":-0.8145161290322581}},"spr23_f7":{"frame":{"x":1246,"y":1216,"w":102,"h":119},"rotated":false,"trimmed":false,"spriteSourceSize":{"x":0,"y":0,"w":102,"h":119},"sourceSize":{"w":102,"h":119},"pivot":{"x":-0.2549019607843137,"y":-0.8403361344537815}},"spr24_f0":{"frame":{"x":1424,"y":1216,"w":89,"h":121},"rotated":false,"trimmed":false,"spriteSourceSize":{"x":0,"y":0,"w":89,"h":121},"sourceSize":{"w":89,"h":121},"pivot":{"x":-0.5056179775280899,"y":-0.7603305785123967}},"spr24_f1":{"frame":{"x":1602,"y":1216,"w":83,"h":125},"rotated":false,"trimmed":false,"spriteSourceSize":{"x":0,"y":0,"w":83,"h":125},"sourceSize":{"w":83,"h":125},"pivot":{"x":-0.5060240963855421,"y":-0.72}},"spr24_f2":{"frame":{"x":1780,"y":1216,"w":79,"h":127},"rotated":false,"trimmed":false,"spriteSourceSize":{"x":0,"y":0,"w":79,"h":127},"sourceSize":{"w":79,"h":127},"pivot":{"x":-0.5063291139240507,"y":-0.6692913385826772}},"spr24_f3":{"frame":{"x":1958,"y":1216,"w":79,"h":130},"rotated":false,"trimmed":false,"spriteSourceSize":{"x":0,"y":0,"w":79,"h":130},"sourceSize":{"w":79,"h":130},"pivot":{"x":-0.5063291139240507,"y":-0.6538461538461539}},"spr24_f4":{"frame":{"x":2136,"y":1216,"w":81,"h":130},"rotated":false,"trimmed":false,"spriteSourceSize":{"x":0,"y":0,"w":81,"h":130},"sourceSize":{"w":81,"h":130},"pivot":{"x":-0.5061728395061729,"y":-0.6692307692307692}},"spr24_f5":{"frame":{"x":2314,"y":1216,"w":85,"h":129},"rotated":false,"trimmed":false,"spriteSourceSize":{"x":0,"y":0,"w":85,"h":129},"sourceSize":{"w":85,"h":129},"pivot":{"x":-0.5058823529411764,"y":-0.6976744186046512}},"spr24_f6":{"frame":{"x":2492,"y":1216,"w":87,"h":126},"rotated":false,"trimmed":false,"spriteSourceSize":{"x":0,"y":0,"w":87,"h":126},"sourceSize":{"w":87,"h":126},"pivot":{"x":-0.5057471264367817,"y":-0.7380952380952381}},"spr24_f7":{"frame":{"x":2670,"y":1216,"w":89,"h":121},"rotated":false,"trimmed":false,"spriteSourceSize":{"x":0,"y":0,"w":89,"h":121},"sourceSize":{"w":89,"h":121},"pivot":{"x":-0.5056179775280899,"y":-0.7603305785123967}},"spr25_f0":{"frame":{"x":2848,"y":1216,"w":99,"h":127},"rotated":false,"trimmed":false,"spriteSourceSize":{"x":0,"y":0,"w":99,"h":127},"sourceSize":{"w":99,"h":127},"pivot":{"x":-0.7272727272727273,"y":-0.7874015748031497}},"spr25_f1":{"frame":{"x":3026,"y":1216,"w":93,"h":125},"rotated":false,"trimmed":false,"spriteSourceSize":{"x":0,"y":0,"w":93,"h":125},"sourceSize":{"w":93,"h":125},"pivot":{"x":-0.7204301075268817,"y":-0.736}},"spr25_f2":{"frame":{"x":3204,"y":1216,"w":88,"h":127},"rotated":false,"trimmed":false,"spriteSourceSize":{"x":0,"y":0,"w":88,"h":127},"sourceSize":{"w":88,"h":127},"pivot":{"x":-0.7159090909090909,"y":-0.6850393700787402}},"spr25_f3":{"frame":{"x":3382,"y":1216,"w":88,"h":130},"rotated":false,"trimmed":false,"spriteSourceSize":{"x":0,"y":0,"w":88,"h":130},"sourceSize":{"w":88,"h":130},"pivot":{"x":-0.7272727272727273,"y":-0.6692307692307692}},"spr25_f4":{"frame":{"x":3560,"y":1216,"w":91,"h":131},"rotated":false,"trimmed":false,"spriteSourceSize":{"x":0,"y":0,"w":91,"h":131},"sourceSize":{"w":91,"h":131},"pivot":{"x":-0.7252747252747253,"y":-0.6870229007633588}},"spr25_f5":{"frame":{"x":3738,"y":1216,"w":94,"h":129},"rotated":false,"trimmed":false,"spriteSourceSize":{"x":0,"y":0,"w":94,"h":129},"sourceSize":{"w":94,"h":129},"pivot":{"x":-0.723404255319149,"y":-0.7209302325581395}},"spr25_f6":{"frame":{"x":3916,"y":1216,"w":97,"h":128},"rotated":false,"trimmed":false,"spriteSourceSize":{"x":0,"y":0,"w":97,"h":128},"sourceSize":{"w":97,"h":128},"pivot":{"x":-0.7319587628865979,"y":-0.7578125}},"spr25_f7":{"frame":{"x":0,"y":1368,"w":99,"h":127},"rotated":false,"trimmed":false,"spriteSourceSize":{"x":0,"y":0,"w":99,"h":127},"sourceSize":{"w":99,"h":127},"pivot":{"x":-0.7272727272727273,"y":-0.7874015748031497}},"spr26_f0":{"frame":{"x":178,"y":1368,"w":153,"h":132},"rotated":false,"trimmed":false,"spriteSourceSize":{"x":0,"y":0,"w":153,"h":132},"sourceSize":{"w":153,"h":132},"pivot":{"x":-0.7581699346405228,"y":-0.9166666666666666}},"spr26_f1":{"frame":{"x":356,"y":1368,"w":154,"h":127},"rotated":false,"trimmed":false,"spriteSourceSize":{"x":0,"y":0,"w":154,"h":127},"sourceSize":{"w":154,"h":127},"pivot":{"x":-0.7597402597402597,"y":-0.9133858267716536}},"spr26_f2":{"frame":{"x":534,"y":1368,"w":152,"h":123},"rotated":false,"trimmed":false,"spriteSourceSize":{"x":0,"y":0,"w":152,"h":123},"sourceSize":{"w":152,"h":123},"pivot":{"x":-0.7631578947368421,"y":-0.9105691056910569}},"spr26_f3":{"frame":{"x":712,"y":1368,"w":152,"h":123},"rotated":false,"trimmed":false,"spriteSourceSize":{"x":0,"y":0,"w":152,"h":123},"sourceSize":{"w":152,"h":123},"pivot":{"x":-0.7631578947368421,"y":-0.9105691056910569}},"spr26_f4":{"frame":{"x":890,"y":1368,"w":152,"h":125},"rotated":false,"trimmed":false,"spriteSourceSize":{"x":0,"y":0,"w":152,"h":125},"sourceSize":{"w":152,"h":125},"pivot":{"x":-0.7631578947368421,"y":-0.912}},"spr26_f5":{"frame":{"x":1068,"y":1368,"w":153,"h":127},"rotated":false,"trimmed":false,"spriteSourceSize":{"x":0,"y":0,"w":153,"h":127},"sourceSize":{"w":153,"h":127},"pivot":{"x":-0.7581699346405228,"y":-0.9133858267716536}},"spr26_f6":{"frame":{"x":1246,"y":1368,"w":153,"h":130},"rotated":false,"trimmed":false,"spriteSourceSize":{"x":0,"y":0,"w":153,"h":130},"sourceSize":{"w":153,"h":130},"pivot":{"x":-0.7581699346405228,"y":-0.9153846153846154}},"spr26_f7":{"frame":{"x":1424,"y":1368,"w":153,"h":132},"rotated":false,"trimmed":false,"spriteSourceSize":{"x":0,"y":0,"w":153,"h":132},"sourceSize":{"w":153,"h":132},"pivot":{"x":-0.7581699346405228,"y":-0.9166666666666666}},"spr27_f0":{"frame":{"x":1602,"y":1368,"w":102,"h":135},"rotated":false,"trimmed":false,"spriteSourceSize":{"x":0,"y":0,"w":102,"h":135},"sourceSize":{"w":102,"h":135},"pivot":{"x":-0.7549019607843137,"y":-0.9777777777777777}},"spr27_f1":{"frame":{"x":1780,"y":1368,"w":102,"h":133},"rotated":false,"trimmed":false,"spriteSourceSize":{"x":0,"y":0,"w":102,"h":133},"sourceSize":{"w":102,"h":133},"pivot":{"x":-0.7549019607843137,"y":-0.9774436090225563}},"spr27_f2":{"frame":{"x":1958,"y":1368,"w":102,"h":131},"rotated":false,"trimmed":false,"spriteSourceSize":{"x":0,"y":0,"w":102,"h":131},"sourceSize":{"w":102,"h":131},"pivot":{"x":-0.7549019607843137,"y":-0.9770992366412213}},"spr27_f3":{"frame":{"x":2136,"y":1368,"w":102,"h":131},"rotated":false,"trimmed":false,"spriteSourceSize":{"x":0,"y":0,"w":102,"h":131},"sourceSize":{"w":102,"h":131},"pivot":{"x":-0.7549019607843137,"y":-0.9770992366412213}},"spr27_f4":{"frame":{"x":2314,"y":1368,"w":102,"h":132},"rotated":false,"trimmed":false,"spriteSourceSize":{"x":0,"y":0,"w":102,"h":132},"sourceSize":{"w":102,"h":132},"pivot":{"x":-0.7549019607843137,"y":-0.9772727272727273}},"spr27_f5":{"frame":{"x":2492,"y":1368,"w":102,"h":133},"rotated":false,"trimmed":false,"spriteSourceSize":{"x":0,"y":0,"w":102,"h":133},"sourceSize":{"w":102,"h":133},"pivot":{"x":-0.7549019607843137,"y":-0.9774436090225563}},"spr27_f6":{"frame":{"x":2670,"y":1368,"w":102,"h":135},"rotated":false,"trimmed":false,"spriteSourceSize":{"x":0,"y":0,"w":102,"h":135},"sourceSize":{"w":102,"h":135},"pivot":{"x":-0.7549019607843137,"y":-0.9777777777777777}},"spr27_f7":{"frame":{"x":2848,"y":1368,"w":102,"h":135},"rotated":false,"trimmed":false,"spriteSourceSize":{"x":0,"y":0,"w":102,"h":135},"sourceSize":{"w":102,"h":135},"pivot":{"x":-0.7549019607843137,"y":-0.9777777777777777}},"spr28_f0":{"frame":{"x":3026,"y":1368,"w":89,"h":136},"rotated":false,"trimmed":false,"spriteSourceSize":{"x":0,"y":0,"w":89,"h":136},"sourceSize":{"w":89,"h":136},"pivot":{"x":-0.5056179775280899,"y":-0.9485294117647058}},"spr28_f1":{"frame":{"x":3204,"y":1368,"w":83,"h":136},"rotated":false,"trimmed":false,"spriteSourceSize":{"x":0,"y":0,"w":83,"h":136},"sourceSize":{"w":83,"h":136},"pivot":{"x":-0.5060240963855421,"y":-0.9485294117647058}},"spr28_f2":{"frame":{"x":3382,"y":1368,"w":79,"h":134},"rotated":false,"trimmed":false,"spriteSourceSize":{"x":0,"y":0,"w":79,"h":134},"sourceSize":{"w":79,"h":134},"pivot":{"x":-0.5063291139240507,"y":-0.9477611940298507}},"spr28_f3":{"frame":{"x":3560,"y":1368,"w":79,"h":133},"rotated":false,"trimmed":false,"spriteSourceSize":{"x":0,"y":0,"w":79,"h":133},"sourceSize":{"w":79,"h":133},"pivot":{"x":-0.5063291139240507,"y":-0.9473684210526315}},"spr28_f4":{"frame":{"x":3738,"y":1368,"w":81,"h":134},"rotated":false,"trimmed":false,"spriteSourceSize":{"x":0,"y":0,"w":81,"h":134},"sourceSize":{"w":81,"h":134},"pivot":{"x":-0.5061728395061729,"y":-0.9477611940298507}},"spr28_f5":{"frame":{"x":3916,"y":1368,"w":85,"h":135},"rotated":false,"trimmed":false,"spriteSourceSize":{"x":0,"y":0,"w":85,"h":135},"sourceSize":{"w":85,"h":135},"pivot":{"x":-0.5058823529411764,"y":-0.9481481481481482}},"spr28_f6":{"frame":{"x":0,"y":1520,"w":87,"h":136},"rotated":false,"trimmed":false,"spriteSourceSize":{"x":0,"y":0,"w":87,"h":136},"sourceSize":{"w":87,"h":136},"pivot":{"x":-0.5057471264367817,"y":-0.9485294117647058}},"spr28_f7":{"frame":{"x":178,"y":1520,"w":89,"h":136},"rotated":false,"trimmed":false,"spriteSourceSize":{"x":0,"y":0,"w":89,"h":136},"sourceSize":{"w":89,"h":136},"pivot":{"x":-0.5056179775280899,"y":-0.9485294117647058}},"spr29_f0":{"frame":{"x":356,"y":1520,"w":100,"h":142},"rotated":false,"trimmed":false,"spriteSourceSize":{"x":0,"y":0,"w":100,"h":142},"sourceSize":{"w":100,"h":142},"pivot":{"x":-0.28,"y":-0.9295774647887324}},"spr29_f1":{"frame":{"x":534,"y":1520,"w":94,"h":141},"rotated":false,"trimmed":false,"spriteSourceSize":{"x":0,"y":0,"w":94,"h":141},"sourceSize":{"w":94,"h":141},"pivot":{"x":-0.2872340425531915,"y":-0.9290780141843972}},"spr29_f2":{"frame":{"x":712,"y":1520,"w":88,"h":138},"rotated":false,"trimmed":false,"spriteSourceSize":{"x":0,"y":0,"w":88,"h":138},"sourceSize":{"w":88,"h":138},"pivot":{"x":-0.2840909090909091,"y":-0.927536231884058}},"spr29_f3":{"frame":{"x":890,"y":1520,"w":89,"h":138},"rotated":false,"trimmed":false,"spriteSourceSize":{"x":0,"y":0,"w":89,"h":138},"sourceSize":{"w":89,"h":138},"pivot":{"x":-0.2808988764044944,"y":-0.927536231884058}},"spr29_f4":{"frame":{"x":1068,"y":1520,"w":92,"h":139},"rotated":false,"trimmed":false,"spriteSourceSize":{"x":0,"y":0,"w":92,"h":139},"sourceSize":{"w":92,"h":139},"pivot":{"x":-0.2826086956521739,"y":-0.9280575539568345}},"spr29_f5":{"frame":{"x":1246,"y":1520,"w":95,"h":140},"rotated":false,"trimmed":false,"spriteSourceSize":{"x":0,"y":0,"w":95,"h":140},"sourceSize":{"w":95,"h":140},"pivot":{"x":-0.28421052631578947,"y":-0.9285714285714286}},"spr29_f6":{"frame":{"x":1424,"y":1520,"w":97,"h":142},"rotated":false,"trimmed":false,"spriteSourceSize":{"x":0,"y":0,"w":97,"h":142},"sourceSize":{"w":97,"h":142},"pivot":{"x":-0.27835051546391754,"y":-0.9295774647887324}},"spr29_f7":{"frame":{"x":1602,"y":1520,"w":100,"h":142},"rotated":false,"trimmed":false,"spriteSourceSize":{"x":0,"y":0,"w":100,"h":142},"sourceSize":{"w":100,"h":142},"pivot":{"x":-0.28,"y":-0.9295774647887324}},"spr2_f0":{"frame":{"x":2848,"y":0,"w":153,"h":132},"rotated":false,"trimmed":false,"spriteSourceSize":{"x":0,"y":0,"w":153,"h":132},"sourceSize":{"w":153,"h":132},"pivot":{"x":-0.7581699346405228,"y":-0.9166666666666666}},"spr2_f1":{"frame":{"x":3026,"y":0,"w":154,"h":132},"rotated":false,"trimmed":false,"spriteSourceSize":{"x":0,"y":0,"w":154,"h":132},"sourceSize":{"w":154,"h":132},"pivot":{"x":-0.7597402597402597,"y":-0.9166666666666666}},"spr2_f2":{"frame":{"x":3204,"y":0,"w":154,"h":130},"rotated":false,"trimmed":false,"spriteSourceSize":{"x":0,"y":0,"w":154,"h":130},"sourceSize":{"w":154,"h":130},"pivot":{"x":-0.7597402597402597,"y":-0.9153846153846154}},"spr2_f3":{"frame":{"x":3382,"y":0,"w":154,"h":130},"rotated":false,"trimmed":false,"spriteSourceSize":{"x":0,"y":0,"w":154,"h":130},"sourceSize":{"w":154,"h":130},"pivot":{"x":-0.7597402597402597,"y":-0.9153846153846154}},"spr2_f4":{"frame":{"x":3560,"y":0,"w":153,"h":130},"rotated":false,"trimmed":false,"spriteSourceSize":{"x":0,"y":0,"w":153,"h":130},"sourceSize":{"w":153,"h":130},"pivot":{"x":-0.7581699346405228,"y":-0.9153846153846154}},"spr2_f5":{"frame":{"x":3738,"y":0,"w":153,"h":131},"rotated":false,"trimmed":false,"spriteSourceSize":{"x":0,"y":0,"w":153,"h":131},"sourceSize":{"w":153,"h":131},"pivot":{"x":-0.7581699346405228,"y":-0.916030534351145}},"spr2_f6":{"frame":{"x":3916,"y":0,"w":154,"h":132},"rotated":false,"trimmed":false,"spriteSourceSize":{"x":0,"y":0,"w":154,"h":132},"sourceSize":{"w":154,"h":132},"pivot":{"x":-0.7597402597402597,"y":-0.9166666666666666}},"spr2_f7":{"frame":{"x":0,"y":152,"w":153,"h":132},"rotated":false,"trimmed":false,"spriteSourceSize":{"x":0,"y":0,"w":153,"h":132},"sourceSize":{"w":153,"h":132},"pivot":{"x":-0.7581699346405228,"y":-0.9166666666666666}},"spr30_f0":{"frame":{"x":1780,"y":1520,"w":153,"h":132},"rotated":false,"trimmed":false,"spriteSourceSize":{"x":0,"y":0,"w":153,"h":132},"sourceSize":{"w":153,"h":132},"pivot":{"x":-0.24836601307189543,"y":-0.9242424242424242}},"spr30_f1":{"frame":{"x":1958,"y":1520,"w":154,"h":126},"rotated":false,"trimmed":false,"spriteSourceSize":{"x":0,"y":0,"w":154,"h":126},"sourceSize":{"w":154,"h":126},"pivot":{"x":-0.24675324675324675,"y":-0.9206349206349206}},"spr30_f2":{"frame":{"x":2136,"y":1520,"w":152,"h":123},"rotated":false,"trimmed":false,"spriteSourceSize":{"x":0,"y":0,"w":152,"h":123},"sourceSize":{"w":152,"h":123},"pivot":{"x":-0.24342105263157895,"y":-0.9186991869918699}},"spr30_f3":{"frame":{"x":2314,"y":1520,"w":152,"h":122},"rotated":false,"trimmed":false,"spriteSourceSize":{"x":0,"y":0,"w":152,"h":122},"sourceSize":{"w":152,"h":122},"pivot":{"x":-0.24342105263157895,"y":-0.9180327868852459}},"spr30_f4":{"frame":{"x":2492,"y":1520,"w":153,"h":124},"rotated":false,"trimmed":false,"spriteSourceSize":{"x":0,"y":0,"w":153,"h":124},"sourceSize":{"w":153,"h":124},"pivot":{"x":-0.24836601307189543,"y":-0.9193548387096774}},"spr30_f5":{"frame":{"x":2670,"y":1520,"w":153,"h":127},"rotated":false,"trimmed":false,"spriteSourceSize":{"x":0,"y":0,"w":153,"h":127},"sourceSize":{"w":153,"h":127},"pivot":{"x":-0.24836601307189543,"y":-0.9212598425196851}},"spr30_f6":{"frame":{"x":2848,"y":1520,"w":154,"h":130},"rotated":false,"trimmed":false,"spriteSourceSize":{"x":0,"y":0,"w":154,"h":130},"sourceSize":{"w":154,"h":130},"pivot":{"x":-0.24675324675324675,"y":-0.9230769230769231}},"spr30_f7":{"frame":{"x":3026,"y":1520,"w":153,"h":132},"rotated":false,"trimmed":false,"spriteSourceSize":{"x":0,"y":0,"w":153,"h":132},"sourceSize":{"w":153,"h":132},"pivot":{"x":-0.24836601307189543,"y":-0.9242424242424242}},"spr31_f0":{"frame":{"x":3204,"y":1520,"w":102,"h":119},"rotated":false,"trimmed":false,"spriteSourceSize":{"x":0,"y":0,"w":102,"h":119},"sourceSize":{"w":102,"h":119},"pivot":{"x":-0.2549019607843137,"y":-0.8403361344537815}},"spr31_f1":{"frame":{"x":3382,"y":1520,"w":102,"h":116},"rotated":false,"trimmed":false,"spriteSourceSize":{"x":0,"y":0,"w":102,"h":116},"sourceSize":{"w":102,"h":116},"pivot":{"x":-0.2549019607843137,"y":-0.8017241379310345}},"spr31_f2":{"frame":{"x":3560,"y":1520,"w":102,"h":117},"rotated":false,"trimmed":false,"spriteSourceSize":{"x":0,"y":0,"w":102,"h":117},"sourceSize":{"w":102,"h":117},"pivot":{"x":-0.2549019607843137,"y":-0.7521367521367521}},"spr31_f3":{"frame":{"x":3738,"y":1520,"w":102,"h":120},"rotated":false,"trimmed":false,"spriteSourceSize":{"x":0,"y":0,"w":102,"h":120},"sourceSize":{"w":102,"h":120},"pivot":{"x":-0.2549019607843137,"y":-0.7333333333333333}},"spr31_f4":{"frame":{"x":3916,"y":1520,"w":102,"h":120},"rotated":false,"trimmed":false,"spriteSourceSize":{"x":0,"y":0,"w":102,"h":120},"sourceSize":{"w":102,"h":120},"pivot":{"x":-0.2549019607843137,"y":-0.75}},"spr31_f5":{"frame":{"x":0,"y":1672,"w":102,"h":120},"rotated":false,"trimmed":false,"spriteSourceSize":{"x":0,"y":0,"w":102,"h":120},"sourceSize":{"w":102,"h":120},"pivot":{"x":-0.2549019607843137,"y":-0.7833333333333333}},"spr31_f6":{"frame":{"x":178,"y":1672,"w":102,"h":120},"rotated":false,"trimmed":false,"spriteSourceSize":{"x":0,"y":0,"w":102,"h":120},"sourceSize":{"w":102,"h":120},"pivot":{"x":-0.2549019607843137,"y":-0.8166666666666667}},"spr31_f7":{"frame":{"x":356,"y":1672,"w":102,"h":119},"rotated":false,"trimmed":false,"spriteSourceSize":{"x":0,"y":0,"w":102,"h":119},"sourceSize":{"w":102,"h":119},"pivot":{"x":-0.2549019607843137,"y":-0.8403361344537815}},"spr32_f0":{"frame":{"x":534,"y":1672,"w":89,"h":121},"rotated":false,"trimmed":false,"spriteSourceSize":{"x":0,"y":0,"w":89,"h":121},"sourceSize":{"w":89,"h":121},"pivot":{"x":-0.5056179775280899,"y":-0.7603305785123967}},"spr32_f1":{"frame":{"x":712,"y":1672,"w":87,"h":131},"rotated":false,"trimmed":false,"spriteSourceSize":{"x":0,"y":0,"w":87,"h":131},"sourceSize":{"w":87,"h":131},"pivot":{"x":-0.5517241379310345,"y":-0.7786259541984732}},"spr32_f2":{"frame":{"x":890,"y":1672,"w":84,"h":143},"rotated":false,"trimmed":false,"spriteSourceSize":{"x":0,"y":0,"w":84,"h":143},"sourceSize":{"w":84,"h":143},"pivot":{"x":-0.6190476190476191,"y":-0.7902097902097902}},"spr32_f3":{"frame":{"x":1068,"y":1672,"w":89,"h":148},"rotated":false,"trimmed":false,"spriteSourceSize":{"x":0,"y":0,"w":89,"h":148},"sourceSize":{"w":89,"h":148},"pivot":{"x":-0.5955056179775281,"y":-0.7905405405405406}},"spr32_f4":{"frame":{"x":1246,"y":1672,"w":90,"h":151},"rotated":false,"trimmed":false,"spriteSourceSize":{"x":0,"y":0,"w":90,"h":151},"sourceSize":{"w":90,"h":151},"pivot":{"x":-0.5555555555555556,"y":-0.7814569536423841}},"spr32_f5":{"frame":{"x":1424,"y":1672,"w":108,"h":145},"rotated":false,"trimmed":false,"spriteSourceSize":{"x":0,"y":0,"w":108,"h":145},"sourceSize":{"w":108,"h":145},"pivot":{"x":-0.4537037037037037,"y":-0.7862068965517242}},"spr32_f6":{"frame":{"x":1602,"y":1672,"w":133,"h":131},"rotated":false,"trimmed":false,"spriteSourceSize":{"x":0,"y":0,"w":133,"h":131},"sourceSize":{"w":133,"h":131},"pivot":{"x":-0.42857142857142855,"y":-0.8244274809160306}},"spr32_f7":{"frame":{"x":1780,"y":1672,"w":136,"h":121},"rotated":false,"trimmed":false,"spriteSourceSize":{"x":0,"y":0,"w":136,"h":121},"sourceSize":{"w":136,"h":121},"pivot":{"x":-0.39705882352941174,"y":-0.8512396694214877}},"spr33_f0":{"frame":{"x":1958,"y":1672,"w":99,"h":127},"rotated":false,"trimmed":false,"spriteSourceSize":{"x":0,"y":0,"w":99,"h":127},"sourceSize":{"w":99,"h":127},"pivot":{"x":-0.7272727272727273,"y":-0.7874015748031497}},"spr33_f1":{"frame":{"x":2136,"y":1672,"w":105,"h":134},"rotated":false,"trimmed":false,"spriteSourceSize":{"x":0,"y":0,"w":105,"h":134},"sourceSize":{"w":105,"h":134},"pivot":{"x":-0.7142857142857143,"y":-0.7985074626865671}},"spr33_f2":{"frame":{"x":2314,"y":1672,"w":111,"h":141},"rotated":false,"trimmed":false,"spriteSourceSize":{"x":0,"y":0,"w":111,"h":141},"sourceSize":{"w":111,"h":141},"pivot":{"x":-0.6576576576576577,"y":-0.8156028368794326}},"spr33_f3":{"frame":{"x":2492,"y":1672,"w":110,"h":144},"rotated":false,"trimmed":false,"spriteSourceSize":{"x":0,"y":0,"w":110,"h":144},"sourceSize":{"w":110,"h":144},"pivot":{"x":-0.5818181818181818,"y":-0.8194444444444444}},"spr33_f4":{"frame":{"x":2670,"y":1672,"w":111,"h":145},"rotated":false,"trimmed":false,"spriteSourceSize":{"x":0,"y":0,"w":111,"h":145},"sourceSize":{"w":111,"h":145},"pivot":{"x":-0.5315315315315315,"y":-0.8275862068965517}},"spr33_f5":{"frame":{"x":2848,"y":1672,"w":124,"h":140},"rotated":false,"trimmed":false,"spriteSourceSize":{"x":0,"y":0,"w":124,"h":140},"sourceSize":{"w":124,"h":140},"pivot":{"x":-0.5241935483870968,"y":-0.8357142857142857}},"spr33_f6":{"frame":{"x":3026,"y":1672,"w":143,"h":124},"rotated":false,"trimmed":false,"spriteSourceSize":{"x":0,"y":0,"w":143,"h":124},"sourceSize":{"w":143,"h":124},"pivot":{"x":-0.43356643356643354,"y":-0.8951612903225806}},"spr33_f7":{"frame":{"x":3204,"y":1672,"w":152,"h":113},"rotated":false,"trimmed":false,"spriteSourceSize":{"x":0,"y":0,"w":152,"h":113},"sourceSize":{"w":152,"h":113},"pivot":{"x":-0.39473684210526316,"y":-0.9292035398230089}},"spr34_f0":{"frame":{"x":3382,"y":1672,"w":153,"h":132},"rotated":false,"trimmed":false,"spriteSourceSize":{"x":0,"y":0,"w":153,"h":132},"sourceSize":{"w":153,"h":132},"pivot":{"x":-0.7581699346405228,"y":-0.9166666666666666}},"spr34_f1":{"frame":{"x":3560,"y":1672,"w":156,"h":136},"rotated":false,"trimmed":false,"spriteSourceSize":{"x":0,"y":0,"w":156,"h":136},"sourceSize":{"w":156,"h":136},"pivot":{"x":-0.7435897435897436,"y":-0.9044117647058824}},"spr34_f2":{"frame":{"x":3738,"y":1672,"w":158,"h":137},"rotated":false,"trimmed":false,"spriteSourceSize":{"x":0,"y":0,"w":158,"h":137},"sourceSize":{"w":158,"h":137},"pivot":{"x":-0.7025316455696202,"y":-0.8905109489051095}},"spr34_f3":{"frame":{"x":3916,"y":1672,"w":161,"h":129},"rotated":false,"trimmed":false,"spriteSourceSize":{"x":0,"y":0,"w":161,"h":129},"sourceSize":{"w":161,"h":129},"pivot":{"x":-0.6645962732919255,"y":-0.8992248062015504}},"spr34_f4":{"frame":{"x":0,"y":1824,"w":165,"h":123},"rotated":false,"trimmed":false,"spriteSourceSize":{"x":0,"y":0,"w":165,"h":123},"sourceSize":{"w":165,"h":123},"pivot":{"x":-0.6424242424242425,"y":-0.9105691056910569}},"spr34_f5":{"frame":{"x":178,"y":1824,"w":167,"h":112},"rotated":false,"trimmed":false,"spriteSourceSize":{"x":0,"y":0,"w":167,"h":112},"sourceSize":{"w":167,"h":112},"pivot":{"x":-0.6047904191616766,"y":-0.9464285714285714}},"spr34_f6":{"frame":{"x":356,"y":1824,"w":174,"h":77},"rotated":false,"trimmed":false,"spriteSourceSize":{"x":0,"y":0,"w":174,"h":77},"sourceSize":{"w":174,"h":77},"pivot":{"x":-0.47701149425287354,"y":-1.1688311688311688}},"spr34_f7":{"frame":{"x":534,"y":1824,"w":177,"h":71},"rotated":false,"trimmed":false,"spriteSourceSize":{"x":0,"y":0,"w":177,"h":71},"sourceSize":{"w":177,"h":71},"pivot":{"x":-0.4124293785310734,"y":-0.9859154929577465}},"spr35_f0":{"frame":{"x":712,"y":1824,"w":102,"h":135},"rotated":false,"trimmed":false,"spriteSourceSize":{"x":0,"y":0,"w":102,"h":135},"sourceSize":{"w":102,"h":135},"pivot":{"x":-0.7549019607843137,"y":-0.9777777777777777}},"spr35_f1":{"frame":{"x":890,"y":1824,"w":99,"h":134},"rotated":false,"trimmed":false,"spriteSourceSize":{"x":0,"y":0,"w":99,"h":134},"sourceSize":{"w":99,"h":134},"pivot":{"x":-0.7474747474747475,"y":-0.9776119402985075}},"spr35_f2":{"frame":{"x":1068,"y":1824,"w":97,"h":125},"rotated":false,"trimmed":false,"spriteSourceSize":{"x":0,"y":0,"w":97,"h":125},"sourceSize":{"w":97,"h":125},"pivot":{"x":-0.7010309278350515,"y":-0.976}},"spr35_f3":{"frame":{"x":1246,"y":1824,"w":94,"h":109},"rotated":false,"trimmed":false,"spriteSourceSize":{"x":0,"y":0,"w":94,"h":109},"sourceSize":{"w":94,"h":109},"pivot":{"x":-0.6276595744680851,"y":-1}},"spr35_f4":{"frame":{"x":1424,"y":1824,"w":94,"h":96},"rotated":false,"trimmed":false,"spriteSourceSize":{"x":0,"y":0,"w":94,"h":96},"sourceSize":{"w":94,"h":96},"pivot":{"x":-0.5319148936170213,"y":-1}},"spr35_f5":{"frame":{"x":1602,"y":1824,"w":111,"h":81},"rotated":false,"trimmed":false,"spriteSourceSize":{"x":0,"y":0,"w":111,"h":81},"sourceSize":{"w":111,"h":81},"pivot":{"x":-0.45045045045045046,"y":-0.9506172839506173}},"spr35_f6":{"frame":{"x":1780,"y":1824,"w":135,"h":82},"rotated":false,"trimmed":false,"spriteSourceSize":{"x":0,"y":0,"w":135,"h":82},"sourceSize":{"w":135,"h":82},"pivot":{"x":-0.4222222222222222,"y":-0.8414634146341463}},"spr35_f7":{"frame":{"x":1958,"y":1824,"w":143,"h":79},"rotated":false,"trimmed":false,"spriteSourceSize":{"x":0,"y":0,"w":143,"h":79},"sourceSize":{"w":143,"h":79},"pivot":{"x":-0.3916083916083916,"y":-0.7468354430379747}},"spr36_f0":{"frame":{"x":2136,"y":1824,"w":89,"h":136},"rotated":false,"trimmed":false,"spriteSourceSize":{"x":0,"y":0,"w":89,"h":136},"sourceSize":{"w":89,"h":136},"pivot":{"x":-0.5056179775280899,"y":-0.9485294117647058}},"spr36_f1":{"frame":{"x":2314,"y":1824,"w":87,"h":136},"rotated":false,"trimmed":false,"spriteSourceSize":{"x":0,"y":0,"w":87,"h":136},"sourceSize":{"w":87,"h":136},"pivot":{"x":-0.45977011494252873,"y":-0.9411764705882353}},"spr36_f2":{"frame":{"x":2492,"y":1824,"w":84,"h":130},"rotated":false,"trimmed":false,"spriteSourceSize":{"x":0,"y":0,"w":84,"h":130},"sourceSize":{"w":84,"h":130},"pivot":{"x":-0.39285714285714285,"y":-0.9461538461538461}},"spr36_f3":{"frame":{"x":2670,"y":1824,"w":89,"h":116},"rotated":false,"trimmed":false,"spriteSourceSize":{"x":0,"y":0,"w":89,"h":116},"sourceSize":{"w":89,"h":116},"pivot":{"x":-0.4157303370786517,"y":-0.9568965517241379}},"spr36_f4":{"frame":{"x":2848,"y":1824,"w":90,"h":100},"rotated":false,"trimmed":false,"spriteSourceSize":{"x":0,"y":0,"w":90,"h":100},"sourceSize":{"w":90,"h":100},"pivot":{"x":-0.45555555555555555,"y":-1}},"spr36_f5":{"frame":{"x":3026,"y":1824,"w":108,"h":93},"rotated":false,"trimmed":false,"spriteSourceSize":{"x":0,"y":0,"w":108,"h":93},"sourceSize":{"w":108,"h":93},"pivot":{"x":-0.5555555555555556,"y":-0.9139784946236559}},"spr36_f6":{"frame":{"x":3204,"y":1824,"w":133,"h":78},"rotated":false,"trimmed":false,"spriteSourceSize":{"x":0,"y":0,"w":133,"h":78},"sourceSize":{"w":133,"h":78},"pivot":{"x":-0.5789473684210527,"y":-0.7692307692307693}},"spr36_f7":{"frame":{"x":3382,"y":1824,"w":136,"h":79},"rotated":false,"trimmed":false,"spriteSourceSize":{"x":0,"y":0,"w":136,"h":79},"sourceSize":{"w":136,"h":79},"pivot":{"x":-0.6102941176470589,"y":-0.7088607594936709}},"spr37_f0":{"frame":{"x":3560,"y":1824,"w":100,"h":142},"rotated":false,"trimmed":false,"spriteSourceSize":{"x":0,"y":0,"w":100,"h":142},"sourceSize":{"w":100,"h":142},"pivot":{"x":-0.28,"y":-0.9295774647887324}},"spr37_f1":{"frame":{"x":3738,"y":1824,"w":106,"h":142},"rotated":false,"trimmed":false,"spriteSourceSize":{"x":0,"y":0,"w":106,"h":142},"sourceSize":{"w":106,"h":142},"pivot":{"x":-0.29245283018867924,"y":-0.9225352112676056}},"spr37_f2":{"frame":{"x":3916,"y":1824,"w":112,"h":136},"rotated":false,"trimmed":false,"spriteSourceSize":{"x":0,"y":0,"w":112,"h":136},"sourceSize":{"w":112,"h":136},"pivot":{"x":-0.3482142857142857,"y":-0.9264705882352942}},"spr37_f3":{"frame":{"x":0,"y":1976,"w":111,"h":124},"rotated":false,"trimmed":false,"spriteSourceSize":{"x":0,"y":0,"w":111,"h":124},"sourceSize":{"w":111,"h":124},"pivot":{"x":-0.43243243243243246,"y":-0.9274193548387096}},"spr37_f4":{"frame":{"x":178,"y":1976,"w":113,"h":114},"rotated":false,"trimmed":false,"spriteSourceSize":{"x":0,"y":0,"w":113,"h":114},"sourceSize":{"w":113,"h":114},"pivot":{"x":-0.4690265486725664,"y":-0.9473684210526315}},"spr37_f5":{"frame":{"x":356,"y":1976,"w":126,"h":109},"rotated":false,"trimmed":false,"spriteSourceSize":{"x":0,"y":0,"w":126,"h":109},"sourceSize":{"w":126,"h":109},"pivot":{"x":-0.47619047619047616,"y":-0.908256880733945}},"spr37_f6":{"frame":{"x":534,"y":1976,"w":145,"h":92},"rotated":false,"trimmed":false,"spriteSourceSize":{"x":0,"y":0,"w":145,"h":92},"sourceSize":{"w":145,"h":92},"pivot":{"x":-0.5655172413793104,"y":-0.8586956521739131}},"spr37_f7":{"frame":{"x":712,"y":1976,"w":153,"h":82},"rotated":false,"trimmed":false,"spriteSourceSize":{"x":0,"y":0,"w":153,"h":82},"sourceSize":{"w":153,"h":82},"pivot":{"x":-0.6078431372549019,"y":-0.7926829268292683}},"spr38_f0":{"frame":{"x":890,"y":1976,"w":153,"h":132},"rotated":false,"trimmed":false,"spriteSourceSize":{"x":0,"y":0,"w":153,"h":132},"sourceSize":{"w":153,"h":132},"pivot":{"x":-0.24836601307189543,"y":-0.9242424242424242}},"spr38_f1":{"frame":{"x":1068,"y":1976,"w":155,"h":133},"rotated":false,"trimmed":false,"spriteSourceSize":{"x":0,"y":0,"w":155,"h":133},"sourceSize":{"w":155,"h":133},"pivot":{"x":-0.2645161290322581,"y":-0.9172932330827067}},"spr38_f2":{"frame":{"x":1246,"y":1976,"w":159,"h":132},"rotated":false,"trimmed":false,"spriteSourceSize":{"x":0,"y":0,"w":159,"h":132},"sourceSize":{"w":159,"h":132},"pivot":{"x":-0.3018867924528302,"y":-0.9166666666666666}},"spr38_f3":{"frame":{"x":1424,"y":1976,"w":163,"h":129},"rotated":false,"trimmed":false,"spriteSourceSize":{"x":0,"y":0,"w":163,"h":129},"sourceSize":{"w":163,"h":129},"pivot":{"x":-0.3374233128834356,"y":-0.9147286821705426}},"spr38_f4":{"frame":{"x":1602,"y":1976,"w":166,"h":131},"rotated":false,"trimmed":false,"spriteSourceSize":{"x":0,"y":0,"w":166,"h":131},"sourceSize":{"w":166,"h":131},"pivot":{"x":-0.3614457831325301,"y":-0.9083969465648855}},"spr38_f5":{"frame":{"x":1780,"y":1976,"w":169,"h":136},"rotated":false,"trimmed":false,"spriteSourceSize":{"x":0,"y":0,"w":169,"h":136},"sourceSize":{"w":169,"h":136},"pivot":{"x":-0.40236686390532544,"y":-0.8676470588235294}},"spr38_f6":{"frame":{"x":1958,"y":1976,"w":175,"h":132},"rotated":false,"trimmed":false,"spriteSourceSize":{"x":0,"y":0,"w":175,"h":132},"sourceSize":{"w":175,"h":132},"pivot":{"x":-0.5257142857142857,"y":-0.8257575757575758}},"spr38_f7":{"frame":{"x":2136,"y":1976,"w":177,"h":118},"rotated":false,"trimmed":false,"spriteSourceSize":{"x":0,"y":0,"w":177,"h":118},"sourceSize":{"w":177,"h":118},"pivot":{"x":-0.5932203389830508,"y":-0.864406779661017}},"spr39_f0":{"frame":{"x":2314,"y":1976,"w":102,"h":119},"rotated":false,"trimmed":false,"spriteSourceSize":{"x":0,"y":0,"w":102,"h":119},"sourceSize":{"w":102,"h":119},"pivot":{"x":-0.2549019607843137,"y":-0.8403361344537815}},"spr39_f1":{"frame":{"x":2492,"y":1976,"w":99,"h":124},"rotated":false,"trimmed":false,"spriteSourceSize":{"x":0,"y":0,"w":99,"h":124},"sourceSize":{"w":99,"h":124},"pivot":{"x":-0.25252525252525254,"y":-0.8548387096774194}},"spr39_f2":{"frame":{"x":2670,"y":1976,"w":99,"h":133},"rotated":false,"trimmed":false,"spriteSourceSize":{"x":0,"y":0,"w":99,"h":133},"sourceSize":{"w":99,"h":133},"pivot":{"x":-0.32323232323232326,"y":-0.8571428571428571}},"spr39_f3":{"frame":{"x":2848,"y":1976,"w":97,"h":140},"rotated":false,"trimmed":false,"spriteSourceSize":{"x":0,"y":0,"w":97,"h":140},"sourceSize":{"w":97,"h":140},"pivot":{"x":-0.4020618556701031,"y":-0.8357142857142857}},"spr39_f4":{"frame":{"x":3026,"y":1976,"w":93,"h":144},"rotated":false,"trimmed":false,"spriteSourceSize":{"x":0,"y":0,"w":93,"h":144},"sourceSize":{"w":93,"h":144},"pivot":{"x":-0.4838709677419355,"y":-0.8125}},"spr39_f5":{"frame":{"x":3204,"y":1976,"w":112,"h":142},"rotated":false,"trimmed":false,"spriteSourceSize":{"x":0,"y":0,"w":112,"h":142},"sourceSize":{"w":112,"h":142},"pivot":{"x":-0.5625,"y":-0.795774647887324}},"spr39_f6":{"frame":{"x":3382,"y":1976,"w":134,"h":130},"rotated":false,"trimmed":false,"spriteSourceSize":{"x":0,"y":0,"w":134,"h":130},"sourceSize":{"w":134,"h":130},"pivot":{"x":-0.6044776119402985,"y":-0.823076923076923}},"spr39_f7":{"frame":{"x":3560,"y":1976,"w":142,"h":122},"rotated":false,"trimmed":false,"spriteSourceSize":{"x":0,"y":0,"w":142,"h":122},"sourceSize":{"w":142,"h":122},"pivot":{"x":-0.6197183098591549,"y":-0.8360655737704918}},"spr3_f0":{"frame":{"x":178,"y":152,"w":102,"h":135},"rotated":false,"trimmed":false,"spriteSourceSize":{"x":0,"y":0,"w":102,"h":135},"sourceSize":{"w":102,"h":135},"pivot":{"x":-0.7549019607843137,"y":-0.9777777777777777}},"spr3_f1":{"frame":{"x":356,"y":152,"w":102,"h":135},"rotated":false,"trimmed":false,"spriteSourceSize":{"x":0,"y":0,"w":102,"h":135},"sourceSize":{"w":102,"h":135},"pivot":{"x":-0.7549019607843137,"y":-0.9777777777777777}},"spr3_f2":{"frame":{"x":534,"y":152,"w":102,"h":134},"rotated":false,"trimmed":false,"spriteSourceSize":{"x":0,"y":0,"w":102,"h":134},"sourceSize":{"w":102,"h":134},"pivot":{"x":-0.7549019607843137,"y":-0.9776119402985075}},"spr3_f3":{"frame":{"x":712,"y":152,"w":102,"h":133},"rotated":false,"trimmed":false,"spriteSourceSize":{"x":0,"y":0,"w":102,"h":133},"sourceSize":{"w":102,"h":133},"pivot":{"x":-0.7549019607843137,"y":-0.9774436090225563}},"spr3_f4":{"frame":{"x":890,"y":152,"w":102,"h":134},"rotated":false,"trimmed":false,"spriteSourceSize":{"x":0,"y":0,"w":102,"h":134},"sourceSize":{"w":102,"h":134},"pivot":{"x":-0.7549019607843137,"y":-0.9776119402985075}},"spr3_f5":{"frame":{"x":1068,"y":152,"w":102,"h":134},"rotated":false,"trimmed":false,"spriteSourceSize":{"x":0,"y":0,"w":102,"h":134},"sourceSize":{"w":102,"h":134},"pivot":{"x":-0.7549019607843137,"y":-0.9776119402985075}},"spr3_f6":{"frame":{"x":1246,"y":152,"w":102,"h":135},"rotated":false,"trimmed":false,"spriteSourceSize":{"x":0,"y":0,"w":102,"h":135},"sourceSize":{"w":102,"h":135},"pivot":{"x":-0.7549019607843137,"y":-0.9777777777777777}},"spr3_f7":{"frame":{"x":1424,"y":152,"w":102,"h":135},"rotated":false,"trimmed":false,"spriteSourceSize":{"x":0,"y":0,"w":102,"h":135},"sourceSize":{"w":102,"h":135},"pivot":{"x":-0.7549019607843137,"y":-0.9777777777777777}},"spr4_f0":{"frame":{"x":1602,"y":152,"w":89,"h":136},"rotated":false,"trimmed":false,"spriteSourceSize":{"x":0,"y":0,"w":89,"h":136},"sourceSize":{"w":89,"h":136},"pivot":{"x":-0.5056179775280899,"y":-0.9485294117647058}},"spr4_f1":{"frame":{"x":1780,"y":152,"w":89,"h":136},"rotated":false,"trimmed":false,"spriteSourceSize":{"x":0,"y":0,"w":89,"h":136},"sourceSize":{"w":89,"h":136},"pivot":{"x":-0.5056179775280899,"y":-0.9485294117647058}},"spr4_f2":{"frame":{"x":1958,"y":152,"w":89,"h":135},"rotated":false,"trimmed":false,"spriteSourceSize":{"x":0,"y":0,"w":89,"h":135},"sourceSize":{"w":89,"h":135},"pivot":{"x":-0.5056179775280899,"y":-0.9481481481481482}},"spr4_f3":{"frame":{"x":2136,"y":152,"w":87,"h":135},"rotated":false,"trimmed":false,"spriteSourceSize":{"x":0,"y":0,"w":87,"h":135},"sourceSize":{"w":87,"h":135},"pivot":{"x":-0.5057471264367817,"y":-0.9481481481481482}},"spr4_f4":{"frame":{"x":2314,"y":152,"w":89,"h":135},"rotated":false,"trimmed":false,"spriteSourceSize":{"x":0,"y":0,"w":89,"h":135},"sourceSize":{"w":89,"h":135},"pivot":{"x":-0.5056179775280899,"y":-0.9481481481481482}},"spr4_f5":{"frame":{"x":2492,"y":152,"w":89,"h":135},"rotated":false,"trimmed":false,"spriteSourceSize":{"x":0,"y":0,"w":89,"h":135},"sourceSize":{"w":89,"h":135},"pivot":{"x":-0.5056179775280899,"y":-0.9481481481481482}},"spr4_f6":{"frame":{"x":2670,"y":152,"w":89,"h":136},"rotated":false,"trimmed":false,"spriteSourceSize":{"x":0,"y":0,"w":89,"h":136},"sourceSize":{"w":89,"h":136},"pivot":{"x":-0.5056179775280899,"y":-0.9485294117647058}},"spr4_f7":{"frame":{"x":2848,"y":152,"w":89,"h":136},"rotated":false,"trimmed":false,"spriteSourceSize":{"x":0,"y":0,"w":89,"h":136},"sourceSize":{"w":89,"h":136},"pivot":{"x":-0.5056179775280899,"y":-0.9485294117647058}},"spr5_f0":{"frame":{"x":3026,"y":152,"w":100,"h":142},"rotated":false,"trimmed":false,"spriteSourceSize":{"x":0,"y":0,"w":100,"h":142},"sourceSize":{"w":100,"h":142},"pivot":{"x":-0.28,"y":-0.9295774647887324}},"spr5_f1":{"frame":{"x":3204,"y":152,"w":100,"h":142},"rotated":false,"trimmed":false,"spriteSourceSize":{"x":0,"y":0,"w":100,"h":142},"sourceSize":{"w":100,"h":142},"pivot":{"x":-0.28,"y":-0.9295774647887324}},"spr5_f2":{"frame":{"x":3382,"y":152,"w":98,"h":141},"rotated":false,"trimmed":false,"spriteSourceSize":{"x":0,"y":0,"w":98,"h":141},"sourceSize":{"w":98,"h":141},"pivot":{"x":-0.2755102040816326,"y":-0.9290780141843972}},"spr5_f3":{"frame":{"x":3560,"y":152,"w":98,"h":140},"rotated":false,"trimmed":false,"spriteSourceSize":{"x":0,"y":0,"w":98,"h":140},"sourceSize":{"w":98,"h":140},"pivot":{"x":-0.2755102040816326,"y":-0.9285714285714286}},"spr5_f4":{"frame":{"x":3738,"y":152,"w":98,"h":141},"rotated":false,"trimmed":false,"spriteSourceSize":{"x":0,"y":0,"w":98,"h":141},"sourceSize":{"w":98,"h":141},"pivot":{"x":-0.2755102040816326,"y":-0.9290780141843972}},"spr5_f5":{"frame":{"x":3916,"y":152,"w":99,"h":141},"rotated":false,"trimmed":false,"spriteSourceSize":{"x":0,"y":0,"w":99,"h":141},"sourceSize":{"w":99,"h":141},"pivot":{"x":-0.2828282828282828,"y":-0.9290780141843972}},"spr5_f6":{"frame":{"x":0,"y":304,"w":100,"h":142},"rotated":false,"trimmed":false,"spriteSourceSize":{"x":0,"y":0,"w":100,"h":142},"sourceSize":{"w":100,"h":142},"pivot":{"x":-0.28,"y":-0.9295774647887324}},"spr5_f7":{"frame":{"x":178,"y":304,"w":100,"h":142},"rotated":false,"trimmed":false,"spriteSourceSize":{"x":0,"y":0,"w":100,"h":142},"sourceSize":{"w":100,"h":142},"pivot":{"x":-0.28,"y":-0.9295774647887324}},"spr6_f0":{"frame":{"x":356,"y":304,"w":153,"h":132},"rotated":false,"trimmed":false,"spriteSourceSize":{"x":0,"y":0,"w":153,"h":132},"sourceSize":{"w":153,"h":132},"pivot":{"x":-0.24836601307189543,"y":-0.9242424242424242}},"spr6_f1":{"frame":{"x":534,"y":304,"w":154,"h":131},"rotated":false,"trimmed":false,"spriteSourceSize":{"x":0,"y":0,"w":154,"h":131},"sourceSize":{"w":154,"h":131},"pivot":{"x":-0.24675324675324675,"y":-0.9236641221374046}},"spr6_f2":{"frame":{"x":712,"y":304,"w":154,"h":129},"rotated":false,"trimmed":false,"spriteSourceSize":{"x":0,"y":0,"w":154,"h":129},"sourceSize":{"w":154,"h":129},"pivot":{"x":-0.24675324675324675,"y":-0.9224806201550387}},"spr6_f3":{"frame":{"x":890,"y":304,"w":154,"h":129},"rotated":false,"trimmed":false,"spriteSourceSize":{"x":0,"y":0,"w":154,"h":129},"sourceSize":{"w":154,"h":129},"pivot":{"x":-0.24675324675324675,"y":-0.9224806201550387}},"spr6_f4":{"frame":{"x":1068,"y":304,"w":154,"h":129},"rotated":false,"trimmed":false,"spriteSourceSize":{"x":0,"y":0,"w":154,"h":129},"sourceSize":{"w":154,"h":129},"pivot":{"x":-0.24675324675324675,"y":-0.9224806201550387}},"spr6_f5":{"frame":{"x":1246,"y":304,"w":153,"h":130},"rotated":false,"trimmed":false,"spriteSourceSize":{"x":0,"y":0,"w":153,"h":130},"sourceSize":{"w":153,"h":130},"pivot":{"x":-0.24836601307189543,"y":-0.9230769230769231}},"spr6_f6":{"frame":{"x":1424,"y":304,"w":154,"h":131},"rotated":false,"trimmed":false,"spriteSourceSize":{"x":0,"y":0,"w":154,"h":131},"sourceSize":{"w":154,"h":131},"pivot":{"x":-0.24675324675324675,"y":-0.9236641221374046}},"spr6_f7":{"frame":{"x":1602,"y":304,"w":153,"h":132},"rotated":false,"trimmed":false,"spriteSourceSize":{"x":0,"y":0,"w":153,"h":132},"sourceSize":{"w":153,"h":132},"pivot":{"x":-0.24836601307189543,"y":-0.9242424242424242}},"spr7_f0":{"frame":{"x":1780,"y":304,"w":102,"h":119},"rotated":false,"trimmed":false,"spriteSourceSize":{"x":0,"y":0,"w":102,"h":119},"sourceSize":{"w":102,"h":119},"pivot":{"x":-0.2549019607843137,"y":-0.8403361344537815}},"spr7_f1":{"frame":{"x":1958,"y":304,"w":102,"h":120},"rotated":false,"trimmed":false,"spriteSourceSize":{"x":0,"y":0,"w":102,"h":120},"sourceSize":{"w":102,"h":120},"pivot":{"x":-0.2549019607843137,"y":-0.8333333333333334}},"spr7_f2":{"frame":{"x":2136,"y":304,"w":103,"h":121},"rotated":false,"trimmed":false,"spriteSourceSize":{"x":0,"y":0,"w":103,"h":121},"sourceSize":{"w":103,"h":121},"pivot":{"x":-0.2524271844660194,"y":-0.8099173553719008}},"spr7_f3":{"frame":{"x":2314,"y":304,"w":102,"h":122},"rotated":false,"trimmed":false,"spriteSourceSize":{"x":0,"y":0,"w":102,"h":122},"sourceSize":{"w":102,"h":122},"pivot":{"x":-0.2549019607843137,"y":-0.8032786885245902}},"spr7_f4":{"frame":{"x":2492,"y":304,"w":103,"h":123},"rotated":false,"trimmed":false,"spriteSourceSize":{"x":0,"y":0,"w":103,"h":123},"sourceSize":{"w":103,"h":123},"pivot":{"x":-0.2524271844660194,"y":-0.7967479674796748}},"spr7_f5":{"frame":{"x":2670,"y":304,"w":103,"h":122},"rotated":false,"trimmed":false,"spriteSourceSize":{"x":0,"y":0,"w":103,"h":122},"sourceSize":{"w":103,"h":122},"pivot":{"x":-0.2524271844660194,"y":-0.8114754098360656}},"spr7_f6":{"frame":{"x":2848,"y":304,"w":102,"h":121},"rotated":false,"trimmed":false,"spriteSourceSize":{"x":0,"y":0,"w":102,"h":121},"sourceSize":{"w":102,"h":121},"pivot":{"x":-0.2549019607843137,"y":-0.8264462809917356}},"spr7_f7":{"frame":{"x":3026,"y":304,"w":102,"h":119},"rotated":false,"trimmed":false,"spriteSourceSize":{"x":0,"y":0,"w":102,"h":119},"sourceSize":{"w":102,"h":119},"pivot":{"x":-0.2549019607843137,"y":-0.8403361344537815}},"spr8_f0":{"frame":{"x":3204,"y":304,"w":89,"h":121},"rotated":false,"trimmed":false,"spriteSourceSize":{"x":0,"y":0,"w":89,"h":121},"sourceSize":{"w":89,"h":121},"pivot":{"x":-0.5056179775280899,"y":-0.7603305785123967}},"spr8_f1":{"frame":{"x":3382,"y":304,"w":87,"h":133},"rotated":false,"trimmed":false,"spriteSourceSize":{"x":0,"y":0,"w":87,"h":133},"sourceSize":{"w":87,"h":133},"pivot":{"x":-0.5057471264367817,"y":-0.7443609022556391}},"spr8_f2":{"frame":{"x":3560,"y":304,"w":85,"h":141},"rotated":false,"trimmed":false,"spriteSourceSize":{"x":0,"y":0,"w":85,"h":141},"sourceSize":{"w":85,"h":141},"pivot":{"x":-0.5058823529411764,"y":-0.7375886524822695}},"spr8_f3":{"frame":{"x":3738,"y":304,"w":87,"h":132},"rotated":false,"trimmed":false,"spriteSourceSize":{"x":0,"y":0,"w":87,"h":132},"sourceSize":{"w":87,"h":132},"pivot":{"x":-0.5057471264367817,"y":-0.75}},"spr8_f4":{"frame":{"x":3916,"y":304,"w":89,"h":121},"rotated":false,"trimmed":false,"spriteSourceSize":{"x":0,"y":0,"w":89,"h":121},"sourceSize":{"w":89,"h":121},"pivot":{"x":-0.5056179775280899,"y":-0.7603305785123967}},"spr8_f5":{"frame":{"x":0,"y":456,"w":87,"h":132},"rotated":false,"trimmed":false,"spriteSourceSize":{"x":0,"y":0,"w":87,"h":132},"sourceSize":{"w":87,"h":132},"pivot":{"x":-0.5057471264367817,"y":-0.75}},"spr8_f6":{"frame":{"x":178,"y":456,"w":85,"h":140},"rotated":false,"trimmed":false,"spriteSourceSize":{"x":0,"y":0,"w":85,"h":140},"sourceSize":{"w":85,"h":140},"pivot":{"x":-0.5058823529411764,"y":-0.7428571428571429}},"spr8_f7":{"frame":{"x":356,"y":456,"w":87,"h":132},"rotated":false,"trimmed":false,"spriteSourceSize":{"x":0,"y":0,"w":87,"h":132},"sourceSize":{"w":87,"h":132},"pivot":{"x":-0.5057471264367817,"y":-0.75}},"spr9_f0":{"frame":{"x":534,"y":456,"w":99,"h":127},"rotated":false,"trimmed":false,"spriteSourceSize":{"x":0,"y":0,"w":99,"h":127},"sourceSize":{"w":99,"h":127},"pivot":{"x":-0.7272727272727273,"y":-0.7874015748031497}},"spr9_f1":{"frame":{"x":712,"y":456,"w":94,"h":130},"rotated":false,"trimmed":false,"spriteSourceSize":{"x":0,"y":0,"w":94,"h":130},"sourceSize":{"w":94,"h":130},"pivot":{"x":-0.7446808510638298,"y":-0.7769230769230769}},"spr9_f2":{"frame":{"x":890,"y":456,"w":89,"h":133},"rotated":false,"trimmed":false,"spriteSourceSize":{"x":0,"y":0,"w":89,"h":133},"sourceSize":{"w":89,"h":133},"pivot":{"x":-0.7865168539325843,"y":-0.7819548872180451}},"spr9_f3":{"frame":{"x":1068,"y":456,"w":94,"h":124},"rotated":false,"trimmed":false,"spriteSourceSize":{"x":0,"y":0,"w":94,"h":124},"sourceSize":{"w":94,"h":124},"pivot":{"x":-0.7659574468085106,"y":-0.8145161290322581}},"spr9_f4":{"frame":{"x":1246,"y":456,"w":101,"h":119},"rotated":false,"trimmed":false,"spriteSourceSize":{"x":0,"y":0,"w":101,"h":119},"sourceSize":{"w":101,"h":119},"pivot":{"x":-0.7524752475247525,"y":-0.8403361344537815}},"spr9_f5":{"frame":{"x":1424,"y":456,"w":93,"h":124},"rotated":false,"trimmed":false,"spriteSourceSize":{"x":0,"y":0,"w":93,"h":124},"sourceSize":{"w":93,"h":124},"pivot":{"x":-0.7741935483870968,"y":-0.8145161290322581}},"spr9_f6":{"frame":{"x":1602,"y":456,"w":92,"h":132},"rotated":false,"trimmed":false,"spriteSourceSize":{"x":0,"y":0,"w":92,"h":132},"sourceSize":{"w":92,"h":132},"pivot":{"x":-0.75,"y":-0.7878787878787878}},"spr9_f7":{"frame":{"x":1780,"y":456,"w":96,"h":130},"rotated":false,"trimmed":false,"spriteSourceSize":{"x":0,"y":0,"w":96,"h":130},"sourceSize":{"w":96,"h":130},"pivot":{"x":-0.7291666666666666,"y":-0.7769230769230769}}},"meta":{"image":"Barlog.png","format":"RGBA8888","size":{"w":4094,"h":2128},"scale":"1"}}